pupdater/__init__.py
pupdater/admin.py
pupdater/apps.py
pupdater/models.py
pupdater/tests.py
pupdater/urls.py
pupdater/views.py
pupdater/cli/__init__.py
pupdater/cli/config.py
pupdater/cli/entrypoint.py
pupdater/install/__init__.py
pupdater/install/install_pupdater.py
pupdater/migrations/0001_initial.py
pupdater/migrations/0002_alter_pipfreezesnapshot_options.py
pupdater/migrations/0003_alter_pipfreezesnapshot_options_and_more.py
pupdater/migrations/0004_alter_pipfreezesnapshot_options_and_more.py
pupdater/migrations/__init__.py
pupdater/static/.DS_Store
pupdater/static/pupdater/styles.css
pupdater/templates/.DS_Store
pupdater/templates/pupdater/.DS_Store
pupdater/templates/pupdater/pupdater_main.html
pupdater/templates/pupdater/requirements_check.html
pupdater-1.1.dist-info/licenses/LICENSE
pupdater-1.1.dist-info/METADATA
pupdater-1.1.dist-info/WHEEL
pupdater-1.1.dist-info/entry_points.txt
pupdater-1.1.dist-info/top_level.txt
pupdater-1.1.dist-info/RECORD
