Metadata-Version: 2.4
Name: pupdater
Version: 1.1
Summary: 🐾 Pupdater: A Django Admin pip manager.
Home-page: https://github.com/WilkoRi/pupdater
Author: Wilko Rietveld
Author-email: Wilko Rietveld <wilkorietveld@icloud.com>
License-Expression: BSD-3-Clause
Requires-Python: >=3.7
License-File: LICENSE
Requires-Dist: django>=3.2
Dynamic: author
Dynamic: home-page
Dynamic: license-file
Dynamic: requires-python
